fractal_tokens/__init__.py
fractal_tokens/exceptions.py
fractal_tokens/py.typed
fractal_tokens/settings.py
fractal_tokens/contrib/__init__.py
fractal_tokens/contrib/identity_platform/__init__.py
fractal_tokens/contrib/identity_platform/jwk.py
fractal_tokens/contrib/identity_platform/payload.py
fractal_tokens/services/__init__.py
fractal_tokens/services/dummy.py
fractal_tokens/services/generic.py
fractal_tokens/services/jwk.py
fractal_tokens/services/jwt/__init__.py
fractal_tokens/services/jwt/asymmetric.py
fractal_tokens/services/jwt/automatic.py
fractal_tokens/services/jwt/symmetric.py
fractal_tokens-1.4.4.dist-info/licenses/LICENSE
fractal_tokens-1.4.4.dist-info/WHEEL
fractal_tokens-1.4.4.dist-info/METADATA
fractal_tokens-1.4.4.dist-info/RECORD
