Metadata-Version: 2.4
Name: fractal-tokens
Version: 1.4.4
Summary: Fractal Tokens provides a flexible way to generate and verify JWT tokens for your Python applications.
Home-page: https://github.com/douwevandermeij/fractal-tokens
Author: Douwe van der Meij
Author-email: douwe@karibu-online.nl
Requires-Python: >=3.8
Classifier: Development Status :: 3 - Alpha
Classifier: Environment :: Web Environment
Classifier: Intended Audience :: Developers
Classifier: License :: OSI Approved :: MIT License
Classifier: Operating System :: OS Independent
Classifier: Programming Language :: Python :: 3
Classifier: Programming Language :: Python
License-File: LICENSE
Requires-Dist: cryptography
Requires-Dist: python-jose
Requires-Dist: black ; extra == "test"
Requires-Dist: flake8 ; extra == "test"
Requires-Dist: isort ; extra == "test"
Provides-Extra: test
